app/__init__.py
app/__main__.py
app/config.py
app/flask_app.py
app/run.py
app/static/__init__.py
app/static/__pycache__/__init__.cpython-39.pyc
app/static/css/base_style.css
app/static/css/depht_style.css
app/static/css/depht_train_style.css
app/static/css/documentation_style.css
app/static/css/models_style.css
app/static/css/program_style.css
app/static/css/results_style.css
app/static/images/SEAPHAGES_Logo.png
app/static/images/hatfull.jpg
app/static/images/help_icon.jpg
app/static/images/help_icon.png
app/static/images/hhmi_logo.jpg
app/static/images/pitt_logo.png
app/static/images/prophage_csv.png
app/static/js/arguments.js
app/static/js/doc_functions.js
app/templates/__init__.py
app/templates/base.html
app/templates/documentation.html
app/templates/loading_base.html
app/templates/program_base.html
app/templates/results_base.html
app/templates/__pycache__/__init__.cpython-39.pyc
app/templates/depht/depht.html
app/templates/depht/loading.html
app/templates/depht/results.html
app/templates/models/models.html
app/templates/train/loading.html
app/templates/train/results.html
app/templates/train/train.html
app/views/__init__.py
app/views/depht.py
app/views/documentation.py
app/views/models.py
app/views/train.py
run_depht/__init__.py
run_depht/run_depht.py
depht_gui-1.0.8.dist-info/LICENSE
depht_gui-1.0.8.dist-info/METADATA
depht_gui-1.0.8.dist-info/WHEEL
depht_gui-1.0.8.dist-info/entry_points.txt
depht_gui-1.0.8.dist-info/top_level.txt
depht_gui-1.0.8.dist-info/RECORD
