Metadata-Version: 2.1
Name: depht-gui
Version: 1.0.8
Summary: Discovery and Extraction of Phages Tool GUI
Home-page: https://github.com/ananya-venbakkam/depht_gui.git
Author: Ananya Venbakkam
Author-email: akv14@pitt.edu
License: UNKNOWN
Platform: UNKNOWN
Classifier: Intended Audience :: Science/Research
Classifier: License :: OSI Approved :: GNU General Public License v3 (GPLv3)
Classifier: Operating System :: MacOS
Classifier: Operating System :: POSIX :: Linux
Classifier: Programming Language :: Python
Classifier: Programming Language :: Python :: 3
Classifier: Programming Language :: Python :: 3 :: Only
Classifier: Programming Language :: Python :: 3.6
Classifier: Programming Language :: Python :: 3.7
Classifier: Programming Language :: Python :: 3.8
Classifier: Programming Language :: Python :: 3.9
Requires-Python: >=3.6
License-File: LICENSE
Requires-Dist: bokeh (~=2.4.2)
Requires-Dist: depht (~=1.1.4)
Requires-Dist: Flask (~=2.1)
Requires-Dist: Jinja2 (~=3.1.1)
Requires-Dist: importlib-resources (~=5.7)
